pytest_djangoapp/__init__.py
pytest_djangoapp/compat.py
pytest_djangoapp/configuration.py
pytest_djangoapp/exceptions.py
pytest_djangoapp/plugin.py
pytest_djangoapp/toolbox.py
pytest_djangoapp/fixtures/__init__.py
pytest_djangoapp/fixtures/admin.py
pytest_djangoapp/fixtures/commands.py
pytest_djangoapp/fixtures/db.py
pytest_djangoapp/fixtures/live.py
pytest_djangoapp/fixtures/mail.py
pytest_djangoapp/fixtures/messages.py
pytest_djangoapp/fixtures/migrations.py
pytest_djangoapp/fixtures/request.py
pytest_djangoapp/fixtures/settings.py
pytest_djangoapp/fixtures/signals.py
pytest_djangoapp/fixtures/templates.py
pytest_djangoapp/fixtures/users.py
pytest_djangoapp/fixtures/utils.py
pytest_djangoapp-1.7.0.dist-info/METADATA
pytest_djangoapp-1.7.0.dist-info/WHEEL
pytest_djangoapp-1.7.0.dist-info/licenses/LICENSE
pytest_djangoapp-1.7.0.dist-info/RECORD
